{
    "01-03 Mo": [
        [
            "Matthew",
            1
        ]
    ],
    "01-04 Tu": [
        [
            "Matthew",
            2
        ]
    ],
    "01-05 We": [
        [
            "Matthew",
            3
        ]
    ],
    "01-06 Th": [
        [
            "Matthew",
            4
        ]
    ],
    "01-07 Fr": [
        [
            "Matthew",
            5
        ]
    ],
    "01-10 Mo": [
        [
            "Matthew",
            6
        ]
    ],
    "01-11 Tu": [
        [
            "Matthew",
            7
        ]
    ],
    "01-12 We": [
        [
            "Matthew",
            8
        ]
    ],
    "01-13 Th": [
        [
            "Matthew",
            9
        ]
    ],
    "01-14 Fr": [
        [
            "Matthew",
            10
        ]
    ],
    "01-17 Mo": [
        [
            "Matthew",
            11
        ]
    ],
    "01-18 Tu": [
        [
            "Matthew",
            12
        ]
    ],
    "01-19 We": [
        [
            "Matthew",
            13
        ]
    ],
    "01-20 Th": [
        [
            "Matthew",
            14
        ]
    ],
    "01-21 Fr": [
        [
            "Matthew",
            15
        ]
    ],
    "01-24 Mo": [
        [
            "Matthew",
            16
        ]
    ],
    "01-25 Tu": [
        [
            "Matthew",
            17
        ]
    ],
    "01-26 We": [
        [
            "Matthew",
            18
        ]
    ],
    "01-27 Th": [
        [
            "Matthew",
            19
        ]
    ],
    "01-28 Fr": [
        [
            "Matthew",
            20
        ]
    ],
    "01-31 Mo": [
        [
            "Matthew",
            21
        ]
    ],
    "02-01 Tu": [
        [
            "Matthew",
            22
        ]
    ],
    "02-02 We": [
        [
            "Matthew",
            23
        ]
    ],
    "02-03 Th": [
        [
            "Matthew",
            24
        ]
    ],
    "02-04 Fr": [
        [
            "Matthew",
            25
        ]
    ],
    "02-07 Mo": [
        [
            "Matthew",
            26
        ]
    ],
    "02-08 Tu": [
        [
            "Matthew",
            27
        ]
    ],
    "02-09 We": [
        [
            "Matthew",
            28
        ]
    ],
    "02-10 Th": [
        [
            "Mark",
            1
        ]
    ],
    "02-11 Fr": [
        [
            "Mark",
            2
        ]
    ],
    "02-14 Mo": [
        [
            "Mark",
            3
        ]
    ],
    "02-15 Tu": [
        [
            "Mark",
            4
        ]
    ],
    "02-16 We": [
        [
            "Mark",
            5
        ]
    ],
    "02-17 Th": [
        [
            "Mark",
            6
        ]
    ],
    "02-18 Fr": [
        [
            "Mark",
            7
        ]
    ],
    "02-21 Mo": [
        [
            "Mark",
            8
        ]
    ],
    "02-22 Tu": [
        [
            "Mark",
            9
        ]
    ],
    "02-23 We": [
        [
            "Mark",
            10
        ]
    ],
    "02-24 Th": [
        [
            "Mark",
            11
        ]
    ],
    "02-25 Fr": [
        [
            "Mark",
            12
        ]
    ],
    "02-28 Mo": [
        [
            "Mark",
            13
        ]
    ],
    "03-01 Tu": [
        [
            "Mark",
            14
        ]
    ],
    "03-02 We": [
        [
            "Mark",
            15
        ]
    ],
    "03-03 Th": [
        [
            "Mark",
            16
        ]
    ],
    "03-04 Fr": [
        [
            "Luke",
            1
        ]
    ],
    "03-07 Mo": [
        [
            "Luke",
            2
        ]
    ],
    "03-08 Tu": [
        [
            "Luke",
            3
        ]
    ],
    "03-09 We": [
        [
            "Luke",
            4
        ]
    ],
    "03-10 Th": [
        [
            "Luke",
            5
        ]
    ],
    "03-11 Fr": [
        [
            "Luke",
            6
        ]
    ],
    "03-14 Mo": [
        [
            "Luke",
            7
        ]
    ],
    "03-15 Tu": [
        [
            "Luke",
            8
        ]
    ],
    "03-16 We": [
        [
            "Luke",
            9
        ]
    ],
    "03-17 Th": [
        [
            "Luke",
            10
        ]
    ],
    "03-18 Fr": [
        [
            "Luke",
            11
        ]
    ],
    "03-21 Mo": [
        [
            "Luke",
            12
        ]
    ],
    "03-22 Tu": [
        [
            "Luke",
            13
        ]
    ],
    "03-23 We": [
        [
            "Luke",
            14
        ]
    ],
    "03-24 Th": [
        [
            "Luke",
            15
        ]
    ],
    "03-25 Fr": [
        [
            "Luke",
            16
        ]
    ],
    "03-28 Mo": [
        [
            "Luke",
            17
        ]
    ],
    "03-29 Tu": [
        [
            "Luke",
            18
        ]
    ],
    "03-30 We": [
        [
            "Luke",
            19
        ]
    ],
    "03-31 Th": [
        [
            "Luke",
            20
        ]
    ],
    "04-01 Fr": [
        [
            "Luke",
            21
        ]
    ],
    "04-04 Mo": [
        [
            "Luke",
            22
        ]
    ],
    "04-05 Tu": [
        [
            "Luke",
            23
        ]
    ],
    "04-06 We": [
        [
            "Luke",
            24
        ]
    ],
    "04-07 Th": [
        [
            "John",
            1
        ]
    ],
    "04-08 Fr": [
        [
            "John",
            2
        ]
    ],
    "04-11 Mo": [
        [
            "John",
            3
        ]
    ],
    "04-12 Tu": [
        [
            "John",
            4
        ]
    ],
    "04-13 We": [
        [
            "John",
            5
        ]
    ],
    "04-14 Th": [
        [
            "John",
            6
        ]
    ],
    "04-15 Fr": [
        [
            "John",
            7
        ]
    ],
    "04-18 Mo": [
        [
            "John",
            8
        ]
    ],
    "04-19 Tu": [
        [
            "John",
            9
        ]
    ],
    "04-20 We": [
        [
            "John",
            10
        ]
    ],
    "04-21 Th": [
        [
            "John",
            11
        ]
    ],
    "04-22 Fr": [
        [
            "John",
            12
        ]
    ],
    "04-25 Mo": [
        [
            "John",
            13
        ]
    ],
    "04-26 Tu": [
        [
            "John",
            14
        ]
    ],
    "04-27 We": [
        [
            "John",
            15
        ]
    ],
    "04-28 Th": [
        [
            "John",
            16
        ]
    ],
    "04-29 Fr": [
        [
            "John",
            17
        ]
    ],
    "05-02 Mo": [
        [
            "John",
            18
        ]
    ],
    "05-03 Tu": [
        [
            "John",
            19
        ]
    ],
    "05-04 We": [
        [
            "John",
            20
        ]
    ],
    "05-05 Th": [
        [
            "John",
            21
        ]
    ],
    "05-06 Fr": [
        [
            "Acts",
            1
        ]
    ],
    "05-09 Mo": [
        [
            "Acts",
            2
        ]
    ],
    "05-10 Tu": [
        [
            "Acts",
            3
        ]
    ],
    "05-11 We": [
        [
            "Acts",
            4
        ]
    ],
    "05-12 Th": [
        [
            "Acts",
            5
        ]
    ],
    "05-13 Fr": [
        [
            "Acts",
            6
        ]
    ],
    "05-16 Mo": [
        [
            "Acts",
            7
        ]
    ],
    "05-17 Tu": [
        [
            "Acts",
            8
        ]
    ],
    "05-18 We": [
        [
            "Acts",
            9
        ]
    ],
    "05-19 Th": [
        [
            "Acts",
            10
        ]
    ],
    "05-20 Fr": [
        [
            "Acts",
            11
        ]
    ],
    "05-23 Mo": [
        [
            "Acts",
            12
        ]
    ],
    "05-24 Tu": [
        [
            "Acts",
            13
        ]
    ],
    "05-25 We": [
        [
            "Acts",
            14
        ]
    ],
    "05-26 Th": [
        [
            "Acts",
            15
        ]
    ],
    "05-27 Fr": [
        [
            "Acts",
            16
        ]
    ],
    "05-30 Mo": [
        [
            "Acts",
            17
        ]
    ],
    "05-31 Tu": [
        [
            "Acts",
            18
        ]
    ],
    "06-01 We": [
        [
            "Acts",
            19
        ]
    ],
    "06-02 Th": [
        [
            "Acts",
            20
        ]
    ],
    "06-03 Fr": [
        [
            "Acts",
            21
        ]
    ],
    "06-06 Mo": [
        [
            "Acts",
            22
        ]
    ],
    "06-07 Tu": [
        [
            "Acts",
            23
        ]
    ],
    "06-08 We": [
        [
            "Acts",
            24
        ]
    ],
    "06-09 Th": [
        [
            "Acts",
            25
        ]
    ],
    "06-10 Fr": [
        [
            "Acts",
            26
        ]
    ],
    "06-13 Mo": [
        [
            "Acts",
            27
        ]
    ],
    "06-14 Tu": [
        [
            "Acts",
            28
        ]
    ],
    "06-15 We": [
        [
            "Romans",
            1
        ]
    ],
    "06-16 Th": [
        [
            "Romans",
            2
        ]
    ],
    "06-17 Fr": [
        [
            "Romans",
            3
        ]
    ],
    "06-20 Mo": [
        [
            "Romans",
            4
        ]
    ],
    "06-21 Tu": [
        [
            "Romans",
            5
        ]
    ],
    "06-22 We": [
        [
            "Romans",
            6
        ]
    ],
    "06-23 Th": [
        [
            "Romans",
            7
        ]
    ],
    "06-24 Fr": [
        [
            "Romans",
            8
        ]
    ],
    "06-27 Mo": [
        [
            "Romans",
            9
        ]
    ],
    "06-28 Tu": [
        [
            "Romans",
            10
        ]
    ],
    "06-29 We": [
        [
            "Romans",
            11
        ]
    ],
    "06-30 Th": [
        [
            "Romans",
            12
        ]
    ],
    "07-01 Fr": [
        [
            "Romans",
            13
        ]
    ],
    "07-04 Mo": [
        [
            "Romans",
            14
        ]
    ],
    "07-05 Tu": [
        [
            "Romans",
            15
        ]
    ],
    "07-06 We": [
        [
            "Romans",
            16
        ]
    ],
    "07-07 Th": [
        [
            "1 Corinthians",
            1
        ]
    ],
    "07-08 Fr": [
        [
            "1 Corinthians",
            2
        ]
    ],
    "07-11 Mo": [
        [
            "1 Corinthians",
            3
        ]
    ],
    "07-12 Tu": [
        [
            "1 Corinthians",
            4
        ]
    ],
    "07-13 We": [
        [
            "1 Corinthians",
            5
        ]
    ],
    "07-14 Th": [
        [
            "1 Corinthians",
            6
        ]
    ],
    "07-15 Fr": [
        [
            "1 Corinthians",
            7
        ]
    ],
    "07-18 Mo": [
        [
            "1 Corinthians",
            8
        ]
    ],
    "07-19 Tu": [
        [
            "1 Corinthians",
            9
        ]
    ],
    "07-20 We": [
        [
            "1 Corinthians",
            10
        ]
    ],
    "07-21 Th": [
        [
            "1 Corinthians",
            11
        ]
    ],
    "07-22 Fr": [
        [
            "1 Corinthians",
            12
        ]
    ],
    "07-25 Mo": [
        [
            "1 Corinthians",
            13
        ]
    ],
    "07-26 Tu": [
        [
            "1 Corinthians",
            14
        ]
    ],
    "07-27 We": [
        [
            "1 Corinthians",
            15
        ]
    ],
    "07-28 Th": [
        [
            "1 Corinthians",
            16
        ]
    ],
    "07-29 Fr": [
        [
            "2 Corinthians",
            1
        ]
    ],
    "08-01 Mo": [
        [
            "2 Corinthians",
            2
        ]
    ],
    "08-02 Tu": [
        [
            "2 Corinthians",
            3
        ]
    ],
    "08-03 We": [
        [
            "2 Corinthians",
            4
        ]
    ],
    "08-04 Th": [
        [
            "2 Corinthians",
            5
        ]
    ],
    "08-05 Fr": [
        [
            "2 Corinthians",
            6
        ]
    ],
    "08-08 Mo": [
        [
            "2 Corinthians",
            7
        ]
    ],
    "08-09 Tu": [
        [
            "2 Corinthians",
            8
        ]
    ],
    "08-10 We": [
        [
            "2 Corinthians",
            9
        ]
    ],
    "08-11 Th": [
        [
            "2 Corinthians",
            10
        ]
    ],
    "08-12 Fr": [
        [
            "2 Corinthians",
            11
        ]
    ],
    "08-15 Mo": [
        [
            "2 Corinthians",
            12
        ]
    ],
    "08-16 Tu": [
        [
            "2 Corinthians",
            13
        ]
    ],
    "08-17 We": [
        [
            "Galatians",
            1
        ]
    ],
    "08-18 Th": [
        [
            "Galatians",
            2
        ]
    ],
    "08-19 Fr": [
        [
            "Galatians",
            3
        ]
    ],
    "08-22 Mo": [
        [
            "Galatians",
            4
        ]
    ],
    "08-23 Tu": [
        [
            "Galatians",
            5
        ]
    ],
    "08-24 We": [
        [
            "Galatians",
            6
        ]
    ],
    "08-25 Th": [
        [
            "Ephesians",
            1
        ]
    ],
    "08-26 Fr": [
        [
            "Ephesians",
            2
        ]
    ],
    "08-29 Mo": [
        [
            "Ephesians",
            3
        ]
    ],
    "08-30 Tu": [
        [
            "Ephesians",
            4
        ]
    ],
    "08-31 We": [
        [
            "Ephesians",
            5
        ]
    ],
    "09-01 Th": [
        [
            "Ephesians",
            6
        ]
    ],
    "09-02 Fr": [
        [
            "Philippians",
            1
        ]
    ],
    "09-05 Mo": [
        [
            "Philippians",
            2
        ]
    ],
    "09-06 Tu": [
        [
            "Philippians",
            3
        ]
    ],
    "09-07 We": [
        [
            "Philippians",
            4
        ]
    ],
    "09-08 Th": [
        [
            "Colossians",
            1
        ]
    ],
    "09-09 Fr": [
        [
            "Colossians",
            2
        ]
    ],
    "09-12 Mo": [
        [
            "Colossians",
            3
        ]
    ],
    "09-13 Tu": [
        [
            "Colossians",
            4
        ]
    ],
    "09-14 We": [
        [
            "1 Thessalonians",
            1
        ]
    ],
    "09-15 Th": [
        [
            "1 Thessalonians",
            2
        ]
    ],
    "09-16 Fr": [
        [
            "1 Thessalonians",
            3
        ]
    ],
    "09-19 Mo": [
        [
            "1 Thessalonians",
            4
        ]
    ],
    "09-20 Tu": [
        [
            "1 Thessalonians",
            5
        ]
    ],
    "09-21 We": [
        [
            "2 Thessalonians",
            1
        ]
    ],
    "09-22 Th": [
        [
            "2 Thessalonians",
            2
        ]
    ],
    "09-23 Fr": [
        [
            "2 Thessalonians",
            3
        ]
    ],
    "09-26 Mo": [
        [
            "1 Timothy",
            1
        ]
    ],
    "09-27 Tu": [
        [
            "1 Timothy",
            2
        ]
    ],
    "09-28 We": [
        [
            "1 Timothy",
            3
        ]
    ],
    "09-29 Th": [
        [
            "1 Timothy",
            4
        ]
    ],
    "09-30 Fr": [
        [
            "1 Timothy",
            5
        ]
    ],
    "10-03 Mo": [
        [
            "1 Timothy",
            6
        ]
    ],
    "10-04 Tu": [
        [
            "2 Timothy",
            1
        ]
    ],
    "10-05 We": [
        [
            "2 Timothy",
            2
        ]
    ],
    "10-06 Th": [
        [
            "2 Timothy",
            3
        ]
    ],
    "10-07 Fr": [
        [
            "2 Timothy",
            4
        ]
    ],
    "10-10 Mo": [
        [
            "Titus",
            1
        ]
    ],
    "10-11 Tu": [
        [
            "Titus",
            2
        ]
    ],
    "10-12 We": [
        [
            "Titus",
            3
        ]
    ],
    "10-13 Th": [
        [
            "Philemon",
            1
        ]
    ],
    "10-14 Fr": [
        [
            "Hebrews",
            1
        ]
    ],
    "10-17 Mo": [
        [
            "Hebrews",
            2
        ]
    ],
    "10-18 Tu": [
        [
            "Hebrews",
            3
        ]
    ],
    "10-19 We": [
        [
            "Hebrews",
            4
        ]
    ],
    "10-20 Th": [
        [
            "Hebrews",
            5
        ]
    ],
    "10-21 Fr": [
        [
            "Hebrews",
            6
        ]
    ],
    "10-24 Mo": [
        [
            "Hebrews",
            7
        ]
    ],
    "10-25 Tu": [
        [
            "Hebrews",
            8
        ]
    ],
    "10-26 We": [
        [
            "Hebrews",
            9
        ]
    ],
    "10-27 Th": [
        [
            "Hebrews",
            10
        ]
    ],
    "10-28 Fr": [
        [
            "Hebrews",
            11
        ]
    ],
    "10-31 Mo": [
        [
            "Hebrews",
            12
        ]
    ],
    "11-01 Tu": [
        [
            "Hebrews",
            13
        ]
    ],
    "11-02 We": [
        [
            "James",
            1
        ]
    ],
    "11-03 Th": [
        [
            "James",
            2
        ]
    ],
    "11-04 Fr": [
        [
            "James",
            3
        ]
    ],
    "11-07 Mo": [
        [
            "James",
            4
        ]
    ],
    "11-08 Tu": [
        [
            "James",
            5
        ]
    ],
    "11-09 We": [
        [
            "1 Peter",
            1
        ]
    ],
    "11-10 Th": [
        [
            "1 Peter",
            2
        ]
    ],
    "11-11 Fr": [
        [
            "1 Peter",
            3
        ]
    ],
    "11-14 Mo": [
        [
            "1 Peter",
            4
        ]
    ],
    "11-15 Tu": [
        [
            "1 Peter",
            5
        ]
    ],
    "11-16 We": [
        [
            "2 Peter",
            1
        ]
    ],
    "11-17 Th": [
        [
            "2 Peter",
            2
        ]
    ],
    "11-18 Fr": [
        [
            "2 Peter",
            3
        ]
    ],
    "11-21 Mo": [
        [
            "1 John",
            1
        ]
    ],
    "11-22 Tu": [
        [
            "1 John",
            2
        ]
    ],
    "11-23 We": [
        [
            "1 John",
            3
        ]
    ],
    "11-24 Th": [
        [
            "1 John",
            4
        ]
    ],
    "11-25 Fr": [
        [
            "1 John",
            5
        ]
    ],
    "11-28 Mo": [
        [
            "2 John",
            1
        ]
    ],
    "11-29 Tu": [
        [
            "3 John",
            1
        ]
    ],
    "11-30 We": [
        [
            "Jude",
            1
        ]
    ],
    "12-01 Th": [
        [
            "Revelation",
            1
        ]
    ],
    "12-02 Fr": [
        [
            "Revelation",
            2
        ]
    ],
    "12-05 Mo": [
        [
            "Revelation",
            3
        ]
    ],
    "12-06 Tu": [
        [
            "Revelation",
            4
        ]
    ],
    "12-07 We": [
        [
            "Revelation",
            5
        ]
    ],
    "12-08 Th": [
        [
            "Revelation",
            6
        ]
    ],
    "12-09 Fr": [
        [
            "Revelation",
            7
        ]
    ],
    "12-12 Mo": [
        [
            "Revelation",
            8
        ]
    ],
    "12-13 Tu": [
        [
            "Revelation",
            9
        ]
    ],
    "12-14 We": [
        [
            "Revelation",
            10
        ]
    ],
    "12-15 Th": [
        [
            "Revelation",
            11
        ]
    ],
    "12-16 Fr": [
        [
            "Revelation",
            12
        ]
    ],
    "12-19 Mo": [
        [
            "Revelation",
            13
        ]
    ],
    "12-20 Tu": [
        [
            "Revelation",
            14
        ]
    ],
    "12-21 We": [
        [
            "Revelation",
            15
        ]
    ],
    "12-22 Th": [
        [
            "Revelation",
            16
        ]
    ],
    "12-23 Fr": [
        [
            "Revelation",
            17
        ]
    ],
    "12-26 Mo": [
        [
            "Revelation",
            18
        ]
    ],
    "12-27 Tu": [
        [
            "Revelation",
            19
        ]
    ],
    "12-28 We": [
        [
            "Revelation",
            20
        ]
    ],
    "12-29 Th": [
        [
            "Revelation",
            21
        ]
    ],
    "12-30 Fr": [
        [
            "Revelation",
            22
        ]
    ]
}